{
  "persons": [
    {
      "id": 1,
      "name": "Arto Hellas",
      "date": "2019-05-30T17:30:31.098Z",
      "number": "0678945342"
    },
    {
      "id": 2,
      "name": "Stella Hellas",
      "date": "2019-05-30T17:30:31.098Z",
      "number": "0678943342"
    },
    {
      "id": 3,
      "name": "Ashaa George",
      "date": "2019-05-30T17:30:31.098Z",
      "number": "0678946633"
    },
    {
      "id": 4,
      "name": "Kishen George",
      "date": "2019-05-30T17:30:31.098Z",
      "number": "0678945533"
    },
    {
      "id": 5,
      "name": "Thenaan",
      "date": "2019-05-30T17:30:31.098Z",
      "number": "0678948897"
    },
    {
      "id": 6,
      "name": "Thylor ",
      "date": "2019-05-30T17:30:31.098Z",
      "number": "0672194887"
    },
    {
      "id": 7,
      "name": "William George",
      "date": "2019-05-30T17:30:31.098Z",
      "number": "0672881947"
    },
    {
      "id": 8,
      "name": "George  David",
      "date": "2019-05-30T17:30:31.098Z",
      "number": "0672687831"
    },
    {
      "id": 9,
      "name": "Lily David",
      "date": "2021-08-03T03:43:04.999Z",
      "number": "798780"
    },
    {
      "id": 10,
      "name": "Sangita Paloo",
      "date": "2021-08-03T03:45:40.246Z",
      "number": "0011-601651719"
    },
    {
      "id": 11,
      "name": "Thivya Jayadevan",
      "date": "2021-08-03T03:47:00.326Z",
      "number": "0011-6034546333"
    },
    {
      "id": 12,
      "name": "Likish Jayadevan",
      "date": "2021-08-03T03:47:43.514Z",
      "number": "3125345643"
    },
    {
      "id": 13,
      "name": "dsaf",
      "date": "2021-08-03T04:37:52.244Z",
      "number": "875987"
    }
  ]
}